<?xml version="1.0" encoding="UTF-8"?>
<dataroot>
<SAMURAIHOD>
<ID>1</ID>
<NAME>HODF1</NAME>
<FPL>13</FPL>
<tup_offset>-1.67049</tup_offset>
<tup_ch2ns>0.0681035</tup_ch2ns>
<tdown_offset>-2.49803</tdown_offset>
<tdown_ch2ns>0.0678947</tdown_ch2ns>
<qped_up>157.644</qped_up>
<qcal_up>0.009810751</qcal_up>
<qped_down>198.953</qped_down>
<qcal_down>0.009652822</qcal_down>
<t_det>32</t_det>
<tup_geo>5</tup_geo>
<tup_ch>0</tup_ch>
<tdown_geo>5</tdown_geo>
<tdown_ch>16</tdown_ch>
<q_det>31</q_det>
<qup_geo>3</qup_geo>
<qup_ch>0</qup_ch>
<qdown_geo>3</qdown_geo>
<qdown_ch>16</qdown_ch>
</SAMURAIHOD>
<SAMURAIHOD>
<ID>2</ID>
<NAME>HODF2</NAME>
<FPL>13</FPL>
<tup_offset>-8.26996</tup_offset>
<tup_ch2ns>0.0668201</tup_ch2ns>
<tdown_offset>-9.36315</tdown_offset>
<tdown_ch2ns>0.0668925</tdown_ch2ns>
<qped_up>110.362</qped_up>
<qcal_up>0.01060248</qcal_up>
<qped_down>133.091</qped_down>
<qcal_down>0.011154011</qcal_down>
<t_det>32</t_det>
<tup_geo>5</tup_geo>
<tup_ch>1</tup_ch>
<tdown_geo>5</tdown_geo>
<tdown_ch>17</tdown_ch>
<q_det>31</q_det>
<qup_geo>3</qup_geo>
<qup_ch>1</qup_ch>
<qdown_geo>3</qdown_geo>
<qdown_ch>17</qdown_ch>
</SAMURAIHOD>
<SAMURAIHOD>
<ID>3</ID>
<NAME>HODF3</NAME>
<FPL>13</FPL>
<tup_offset>-9.86454</tup_offset>
<tup_ch2ns>0.0691588</tup_ch2ns>
<tdown_offset>-10.8664</tdown_offset>
<tdown_ch2ns>0.0687935</tdown_ch2ns>
<qped_up>360.059</qped_up>
<qcal_up>0.010568996</qcal_up>
<qped_down>51.7201</qped_down>
<qcal_down>0.009913971</qcal_down>
<t_det>32</t_det>
<tup_geo>5</tup_geo>
<tup_ch>2</tup_ch>
<tdown_geo>5</tdown_geo>
<tdown_ch>18</tdown_ch>
<q_det>31</q_det>
<qup_geo>3</qup_geo>
<qup_ch>2</qup_ch>
<qdown_geo>3</qdown_geo>
<qdown_ch>18</qdown_ch>
</SAMURAIHOD>
<SAMURAIHOD>
<ID>4</ID>
<NAME>HODF4</NAME>
<FPL>13</FPL>
<tup_offset>-9.90756</tup_offset>
<tup_ch2ns>0.0684585</tup_ch2ns>
<tdown_offset>-10.6325</tdown_offset>
<tdown_ch2ns>0.0668119</tdown_ch2ns>
<qped_up>87.0029</qped_up>
<qcal_up>0.010140294</qcal_up>
<qped_down>131.709</qped_down>
<qcal_down>0.010010761</qcal_down>
<t_det>32</t_det>
<tup_geo>5</tup_geo>
<tup_ch>3</tup_ch>
<tdown_geo>5</tdown_geo>
<tdown_ch>19</tdown_ch>
<q_det>31</q_det>
<qup_geo>3</qup_geo>
<qup_ch>3</qup_ch>
<qdown_geo>3</qdown_geo>
<qdown_ch>19</qdown_ch>
</SAMURAIHOD>
<SAMURAIHOD>
<ID>5</ID>
<NAME>HODF5</NAME>
<FPL>13</FPL>
<tup_offset>-7.361</tup_offset>
<tup_ch2ns>0.0681377</tup_ch2ns>
<tdown_offset>-8.81184</tdown_offset>
<tdown_ch2ns>0.0706081</tdown_ch2ns>
<qped_up>163.775</qped_up>
<qcal_up>0.010323237</qcal_up>
<qped_down>150.98</qped_down>
<qcal_down>0.008665185</qcal_down>
<t_det>32</t_det>
<tup_geo>5</tup_geo>
<tup_ch>4</tup_ch>
<tdown_geo>5</tdown_geo>
<tdown_ch>20</tdown_ch>
<q_det>31</q_det>
<qup_geo>3</qup_geo>
<qup_ch>4</qup_ch>
<qdown_geo>3</qdown_geo>
<qdown_ch>20</qdown_ch>
</SAMURAIHOD>
<SAMURAIHOD>
<ID>6</ID>
<NAME>HODF6</NAME>
<FPL>13</FPL>
<tup_offset>-2.94986</tup_offset>
<tup_ch2ns>0.0686917</tup_ch2ns>
<tdown_offset>-2.90241</tdown_offset>
<tdown_ch2ns>0.0684331</tdown_ch2ns>
<qped_up>84.933</qped_up>
<qcal_up>0.008306913</qcal_up>
<qped_down>136.092</qped_down>
<qcal_down>0.009665612</qcal_down>
<t_det>32</t_det>
<tup_geo>5</tup_geo>
<tup_ch>5</tup_ch>
<tdown_geo>5</tdown_geo>
<tdown_ch>21</tdown_ch>
<q_det>31</q_det>
<qup_geo>3</qup_geo>
<qup_ch>5</qup_ch>
<qdown_geo>3</qdown_geo>
<qdown_ch>21</qdown_ch>
</SAMURAIHOD>
<SAMURAIHOD>
<ID>7</ID>
<NAME>HODF7</NAME>
<FPL>13</FPL>
<tup_offset>-9.08552</tup_offset>
<tup_ch2ns>0.0690082</tup_ch2ns>
<tdown_offset>-7.01038</tdown_offset>
<tdown_ch2ns>0.0674848</tdown_ch2ns>
<qped_up>212.433</qped_up>
<qcal_up>0.009339855</qcal_up>
<qped_down>37.8798</qped_down>
<qcal_down>0.009833185</qcal_down>
<t_det>32</t_det>
<tup_geo>5</tup_geo>
<tup_ch>6</tup_ch>
<tdown_geo>5</tdown_geo>
<tdown_ch>22</tdown_ch>
<q_det>31</q_det>
<qup_geo>3</qup_geo>
<qup_ch>6</qup_ch>
<qdown_geo>3</qdown_geo>
<qdown_ch>22</qdown_ch>
</SAMURAIHOD>
<SAMURAIHOD>
<ID>8</ID>
<NAME>HODF8</NAME>
<FPL>13</FPL>
<tup_offset>-1.63921</tup_offset>
<tup_ch2ns>0.0692062</tup_ch2ns>
<tdown_offset>-9.48216</tdown_offset>
<tdown_ch2ns>0.0696733</tdown_ch2ns>
<qped_up>173.882</qped_up>
<qcal_up>0.009125434</qcal_up>
<qped_down>129.736</qped_down>
<qcal_down>0.009725313</qcal_down>
<t_det>32</t_det>
<tup_geo>5</tup_geo>
<tup_ch>7</tup_ch>
<tdown_geo>5</tdown_geo>
<tdown_ch>23</tdown_ch>
<q_det>31</q_det>
<qup_geo>3</qup_geo>
<qup_ch>7</qup_ch>
<qdown_geo>3</qdown_geo>
<qdown_ch>23</qdown_ch>
</SAMURAIHOD>
<SAMURAIHOD>
<ID>9</ID>
<NAME>HODF9</NAME>
<FPL>13</FPL>
<tup_offset>-9.27826</tup_offset>
<tup_ch2ns>0.0667901</tup_ch2ns>
<tdown_offset>-9.56562</tdown_offset>
<tdown_ch2ns>0.0677957</tdown_ch2ns>
<qped_up>149.215</qped_up>
<qcal_up>0.009770198</qcal_up>
<qped_down>194.869</qped_down>
<qcal_down>0.010026599</qcal_down>
<t_det>32</t_det>
<tup_geo>5</tup_geo>
<tup_ch>8</tup_ch>
<tdown_geo>5</tdown_geo>
<tdown_ch>24</tdown_ch>
<q_det>31</q_det>
<qup_geo>3</qup_geo>
<qup_ch>8</qup_ch>
<qdown_geo>3</qdown_geo>
<qdown_ch>24</qdown_ch>
</SAMURAIHOD>
<SAMURAIHOD>
<ID>10</ID>
<NAME>HODF10</NAME>
<FPL>13</FPL>
<tup_offset>-5.20193</tup_offset>
<tup_ch2ns>0.0679847</tup_ch2ns>
<tdown_offset>-4.75265</tdown_offset>
<tdown_ch2ns>0.0682531</tdown_ch2ns>
<qped_up>102.294</qped_up>
<qcal_up>0.0090774</qcal_up>
<qped_down>147.198</qped_down>
<qcal_down>0.010926489</qcal_down>
<t_det>32</t_det>
<tup_geo>5</tup_geo>
<tup_ch>9</tup_ch>
<tdown_geo>5</tdown_geo>
<tdown_ch>25</tdown_ch>
<q_det>31</q_det>
<qup_geo>3</qup_geo>
<qup_ch>9</qup_ch>
<qdown_geo>3</qdown_geo>
<qdown_ch>25</qdown_ch>
</SAMURAIHOD>
<SAMURAIHOD>
<ID>11</ID>
<NAME>HODF11</NAME>
<FPL>13</FPL>
<tup_offset>-9.1937</tup_offset>
<tup_ch2ns>0.0676567</tup_ch2ns>
<tdown_offset>-9.57095</tdown_offset>
<tdown_ch2ns>0.0679103</tdown_ch2ns>
<qped_up>341.222</qped_up>
<qcal_up>0.008683142</qcal_up>
<qped_down>187.042</qped_down>
<qcal_down>0.009392542</qcal_down>
<t_det>32</t_det>
<tup_geo>5</tup_geo>
<tup_ch>10</tup_ch>
<tdown_geo>5</tdown_geo>
<tdown_ch>26</tdown_ch>
<q_det>31</q_det>
<qup_geo>3</qup_geo>
<qup_ch>10</qup_ch>
<qdown_geo>3</qdown_geo>
<qdown_ch>26</qdown_ch>
</SAMURAIHOD>
<SAMURAIHOD>
<ID>12</ID>
<NAME>HODF12</NAME>
<FPL>13</FPL>
<tup_offset>-8.88445</tup_offset>
<tup_ch2ns>0.0678279</tup_ch2ns>
<tdown_offset>-9.35376</tdown_offset>
<tdown_ch2ns>0.0682707</tdown_ch2ns>
<qped_up>115.516</qped_up>
<qcal_up>0.0091778</qcal_up>
<qped_down>54.9997</qped_down>
<qcal_down>0.009844632</qcal_down>
<t_det>32</t_det>
<tup_geo>5</tup_geo>
<tup_ch>11</tup_ch>
<tdown_geo>5</tdown_geo>
<tdown_ch>27</tdown_ch>
<q_det>31</q_det>
<qup_geo>3</qup_geo>
<qup_ch>11</qup_ch>
<qdown_geo>3</qdown_geo>
<qdown_ch>27</qdown_ch>
</SAMURAIHOD>
<SAMURAIHOD>
<ID>13</ID>
<NAME>HODF13</NAME>
<FPL>13</FPL>
<tup_offset>-9.07371</tup_offset>
<tup_ch2ns>0.0688717</tup_ch2ns>
<tdown_offset>-0.908673</tdown_offset>
<tdown_ch2ns>0.0677043</tdown_ch2ns>
<qped_up>74.3497</qped_up>
<qcal_up>0.010175584</qcal_up>
<qped_down>89.235</qped_down>
<qcal_down>0.010163885</qcal_down>
<t_det>32</t_det>
<tup_geo>5</tup_geo>
<tup_ch>12</tup_ch>
<tdown_geo>5</tdown_geo>
<tdown_ch>28</tdown_ch>
<q_det>31</q_det>
<qup_geo>3</qup_geo>
<qup_ch>12</qup_ch>
<qdown_geo>3</qdown_geo>
<qdown_ch>28</qdown_ch>
</SAMURAIHOD>
<SAMURAIHOD>
<ID>14</ID>
<NAME>HODF14</NAME>
<FPL>13</FPL>
<tup_offset>-10.0178</tup_offset>
<tup_ch2ns>0.0677767</tup_ch2ns>
<tdown_offset>-0.67663</tdown_offset>
<tdown_ch2ns>0.0671599</tdown_ch2ns>
<qped_up>41.2344</qped_up>
<qcal_up>0.009322801</qcal_up>
<qped_down>321.275</qped_down>
<qcal_down>0.010067014</qcal_down>
<t_det>32</t_det>
<tup_geo>5</tup_geo>
<tup_ch>13</tup_ch>
<tdown_geo>5</tdown_geo>
<tdown_ch>29</tdown_ch>
<q_det>31</q_det>
<qup_geo>3</qup_geo>
<qup_ch>13</qup_ch>
<qdown_geo>3</qdown_geo>
<qdown_ch>29</qdown_ch>
</SAMURAIHOD>
<SAMURAIHOD>
<ID>15</ID>
<NAME>HODF15</NAME>
<FPL>13</FPL>
<tup_offset>-9.84524</tup_offset>
<tup_ch2ns>0.0685507</tup_ch2ns>
<tdown_offset>-10.8151</tdown_offset>
<tdown_ch2ns>0.0677849</tdown_ch2ns>
<qped_up>60.773</qped_up>
<qcal_up>0.00963631</qcal_up>
<qped_down>108.226</qped_down>
<qcal_down>0.010062119</qcal_down>
<t_det>32</t_det>
<tup_geo>5</tup_geo>
<tup_ch>14</tup_ch>
<tdown_geo>5</tdown_geo>
<tdown_ch>30</tdown_ch>
<q_det>31</q_det>
<qup_geo>3</qup_geo>
<qup_ch>14</qup_ch>
<qdown_geo>3</qdown_geo>
<qdown_ch>30</qdown_ch>
</SAMURAIHOD>
<SAMURAIHOD>
<ID>16</ID>
<NAME>HODF16</NAME>
<FPL>13</FPL>
<tup_offset>-9.58382</tup_offset>
<tup_ch2ns>0.0684444</tup_ch2ns>
<tdown_offset>-9.859</tdown_offset>
<tdown_ch2ns>0.0689326</tdown_ch2ns>
<qped_up>166.061</qped_up>
<qcal_up>0.01166335</qcal_up>
<qped_down>120.16</qped_down>
<qcal_down>0.010580134</qcal_down>
<t_det>32</t_det>
<tup_geo>5</tup_geo>
<tup_ch>15</tup_ch>
<tdown_geo>5</tdown_geo>
<tdown_ch>31</tdown_ch>
<q_det>31</q_det>
<qup_geo>3</qup_geo>
<qup_ch>15</qup_ch>
<qdown_geo>3</qdown_geo>
<qdown_ch>31</qdown_ch>
</SAMURAIHOD>
<SAMURAIHOD>
<ID>17</ID>
<NAME>HODF17</NAME>
<FPL>13</FPL>
<tup_offset>-3.24614</tup_offset>
<tup_ch2ns>0.0680538</tup_ch2ns>
<tdown_offset>-9.96764</tdown_offset>
<tdown_ch2ns>0.0679678</tdown_ch2ns>
<qped_up>219.071</qped_up>
<qcal_up>0.009663677</qcal_up>
<qped_down>175.644</qped_down>
<qcal_down>0.009716739</qcal_down>
<t_det>32</t_det>
<tup_geo>6</tup_geo>
<tup_ch>0</tup_ch>
<tdown_geo>6</tdown_geo>
<tdown_ch>8</tdown_ch>
<q_det>31</q_det>
<qup_geo>4</qup_geo>
<qup_ch>0</qup_ch>
<qdown_geo>4</qdown_geo>
<qdown_ch>8</qdown_ch>
</SAMURAIHOD>
<SAMURAIHOD>
<ID>18</ID>
<NAME>HODF18</NAME>
<FPL>13</FPL>
<tup_offset>-0.851623</tup_offset>
<tup_ch2ns>0.0696012</tup_ch2ns>
<tdown_offset>-7.30437</tdown_offset>
<tdown_ch2ns>0.0695076</tdown_ch2ns>
<qped_up>229.704</qped_up>
<qcal_up>0.009912411</qcal_up>
<qped_down>171.022</qped_down>
<qcal_down>0.010349262</qcal_down>
<t_det>32</t_det>
<tup_geo>6</tup_geo>
<tup_ch>1</tup_ch>
<tdown_geo>6</tdown_geo>
<tdown_ch>9</tdown_ch>
<q_det>31</q_det>
<qup_geo>4</qup_geo>
<qup_ch>1</qup_ch>
<qdown_geo>4</qdown_geo>
<qdown_ch>9</qdown_ch>
</SAMURAIHOD>
<SAMURAIHOD>
<ID>19</ID>
<NAME>HODF19</NAME>
<FPL>13</FPL>
<tup_offset>-4.87628</tup_offset>
<tup_ch2ns>0.06889</tup_ch2ns>
<tdown_offset>-9.75491</tdown_offset>
<tdown_ch2ns>0.0704274</tdown_ch2ns>
<qped_up>219.474</qped_up>
<qcal_up>0.009258076</qcal_up>
<qped_down>185.174</qped_down>
<qcal_down>0.010260458</qcal_down>
<t_det>32</t_det>
<tup_geo>6</tup_geo>
<tup_ch>2</tup_ch>
<tdown_geo>6</tdown_geo>
<tdown_ch>10</tdown_ch>
<q_det>31</q_det>
<qup_geo>4</qup_geo>
<qup_ch>2</qup_ch>
<qdown_geo>4</qdown_geo>
<qdown_ch>10</qdown_ch>
</SAMURAIHOD>
<SAMURAIHOD>
<ID>20</ID>
<NAME>HODF20</NAME>
<FPL>13</FPL>
<tup_offset>-4.74927</tup_offset>
<tup_ch2ns>0.0693353</tup_ch2ns>
<tdown_offset>-2.34037</tdown_offset>
<tdown_ch2ns>0.068342</tdown_ch2ns>
<qped_up>95.8311</qped_up>
<qcal_up>0.010435438</qcal_up>
<qped_down>138.943</qped_down>
<qcal_down>0.010896547</qcal_down>
<t_det>32</t_det>
<tup_geo>6</tup_geo>
<tup_ch>3</tup_ch>
<tdown_geo>6</tdown_geo>
<tdown_ch>11</tdown_ch>
<q_det>31</q_det>
<qup_geo>4</qup_geo>
<qup_ch>3</qup_ch>
<qdown_geo>4</qdown_geo>
<qdown_ch>11</qdown_ch>
</SAMURAIHOD>
<SAMURAIHOD>
<ID>21</ID>
<NAME>HODF21</NAME>
<FPL>13</FPL>
<tup_offset>-2.02631</tup_offset>
<tup_ch2ns>0.0694755</tup_ch2ns>
<tdown_offset>-2.75522</tdown_offset>
<tdown_ch2ns>0.068797</tdown_ch2ns>
<qped_up>204.839</qped_up>
<qcal_up>0.010225794</qcal_up>
<qped_down>221.803</qped_down>
<qcal_down>0.010880179</qcal_down>
<t_det>32</t_det>
<tup_geo>6</tup_geo>
<tup_ch>4</tup_ch>
<tdown_geo>6</tdown_geo>
<tdown_ch>12</tdown_ch>
<q_det>31</q_det>
<qup_geo>4</qup_geo>
<qup_ch>4</qup_ch>
<qdown_geo>4</qdown_geo>
<qdown_ch>12</qdown_ch>
</SAMURAIHOD>
<SAMURAIHOD>
<ID>22</ID>
<NAME>HODF22</NAME>
<FPL>13</FPL>
<tup_offset>-6.26256</tup_offset>
<tup_ch2ns>0.0693064</tup_ch2ns>
<tdown_offset>-2.14227</tdown_offset>
<tdown_ch2ns>0.0682735</tdown_ch2ns>
<qped_up>170.281</qped_up>
<qcal_up>0.010593508</qcal_up>
<qped_down>160.929</qped_down>
<qcal_down>0.009650617</qcal_down>
<t_det>32</t_det>
<tup_geo>6</tup_geo>
<tup_ch>5</tup_ch>
<tdown_geo>6</tdown_geo>
<tdown_ch>13</tdown_ch>
<q_det>31</q_det>
<qup_geo>4</qup_geo>
<qup_ch>5</qup_ch>
<qdown_geo>4</qdown_geo>
<qdown_ch>13</qdown_ch>
</SAMURAIHOD>
<SAMURAIHOD>
<ID>23</ID>
<NAME>HODF23</NAME>
<FPL>13</FPL>
<tup_offset>-7.28619</tup_offset>
<tup_ch2ns>0.0687162</tup_ch2ns>
<tdown_offset>-2.69726</tdown_offset>
<tdown_ch2ns>0.0699521</tdown_ch2ns>
<qped_up>179.544</qped_up>
<qcal_up>0.010512565</qcal_up>
<qped_down>123.726</qped_down>
<qcal_down>0.010871197</qcal_down>
<t_det>32</t_det>
<tup_geo>6</tup_geo>
<tup_ch>6</tup_ch>
<tdown_geo>6</tdown_geo>
<tdown_ch>14</tdown_ch>
<q_det>31</q_det>
<qup_geo>4</qup_geo>
<qup_ch>6</qup_ch>
<qdown_geo>4</qdown_geo>
<qdown_ch>14</qdown_ch>
</SAMURAIHOD>
<SAMURAIHOD>
<ID>24</ID>
<NAME>HODF24</NAME>
<FPL>13</FPL>
<tup_offset>-1.43638</tup_offset>
<tup_ch2ns>0.0689191</tup_ch2ns>
<tdown_offset>-2.81821</tdown_offset>
<tdown_ch2ns>0.0691658</tdown_ch2ns>
<qped_up>168.084</qped_up>
<qcal_up>0.010047961</qcal_up>
<qped_down>241.735</qped_down>
<qcal_down>0.010533423</qcal_down>
<t_det>32</t_det>
<tup_geo>6</tup_geo>
<tup_ch>7</tup_ch>
<tdown_geo>6</tdown_geo>
<tdown_ch>15</tdown_ch>
<q_det>31</q_det>
<qup_geo>4</qup_geo>
<qup_ch>7</qup_ch>
<qdown_geo>4</qdown_geo>
<qdown_ch>15</qdown_ch>
</SAMURAIHOD>
</dataroot>
